[
  {
    "id":1,
    "image": "Bane.jpg"
  },
  {
    "id":2,
    "image": "Batman.jpg"
  },
  {
    "id":3,
    "image": "Catwoman.jpg"
  },
  {
    "id":4,
    "image": "Deathstroke.jpg"
  },
  {
    "id":5,
    "image": "Joker.jpg"
  },
  {
    "id":6,
    "image": "MrFreeze.jpg"
  },
  {
    "id":7,
    "image": "Nightwing.jpg"
  },
  {
    "id":8,
    "image": "Penguin.jpg"
  },
  {
    "id":9,
    "image": "PoisonIvy.jpg"
  },
  {
    "id":10,
    "image": "Redhood.jpg"
  },
  {
    "id":11,
    "image": "Robin.jpg"
  },
  {
    "id":12,
    "image": "TwoFace.jpg"
  }
]
